Metadata-Version: 2.1
Name: Alto-updateStatus
Version: 0.0.3
Summary: Execute PATCH api to update service status
Author: Kanokpich
License-File: LICENSE
